akkio/__init__.py
akkio-1.0.5.dist-info/LICENSE
akkio-1.0.5.dist-info/METADATA
akkio-1.0.5.dist-info/WHEEL
akkio-1.0.5.dist-info/top_level.txt
akkio-1.0.5.dist-info/RECORD
