Metadata-Version: 2.1
Name: akkio
Version: 1.0.5
Summary: Convenient access to the Akkio API from python
Home-page: https://github.com/akkio-inc/akkio-python
Author: Abraham Parangi
Author-email: abe@akk.io
License: UNKNOWN
Project-URL: Bug Tracker, https://github.com/akkio-inc/akkio-python/issues
Platform: UNKNOWN
Classifier: Programming Language :: Python :: 3
Classifier: License :: OSI Approved :: MIT License
Classifier: Operating System :: OS Independent
Requires-Python: >=3.6
